Metadata-Version: 2.2
Name: my-regression-model
Version: 0.0.8
Summary: Example regression model package .
Home-page: https://github.com/meens174/Deployment
Author: MV
Author-email: meens.v1986@gmail.com
License: BSD-3
Classifier: License :: OSI Approved :: MIT License
Classifier: Programming Language :: Python
Classifier: Programming Language :: Python :: 3
Classifier: Programming Language :: Python :: 3.6
Classifier: Programming Language :: Python :: 3.7
Classifier: Programming Language :: Python :: 3.8
Classifier: Programming Language :: Python :: 3.9
Classifier: Programming Language :: Python :: 3.10
Classifier: Programming Language :: Python :: 3.11
Classifier: Programming Language :: Python :: 3.12
Classifier: Programming Language :: Python :: 3.13
Classifier: Programming Language :: Python :: Implementation :: CPython
Classifier: Programming Language :: Python :: Implementation :: PyPy
Requires-Python: >=3.6.0
Requires-Dist: pydantic<2.0.0,>=1.8.1
Requires-Dist: scikit-learn<2.0.0,>=1.1.3
Requires-Dist: strictyaml<2.0.0,>=1.3.2
Requires-Dist: ruamel.yaml<1.0.0,>=0.16.12
Requires-Dist: feature-engine<1.6.0,>=1.0.2
Requires-Dist: joblib<2.0.0,>=1.0.1
Requires-Dist: numpy
Requires-Dist: pandas
Dynamic: author
Dynamic: author-email
Dynamic: classifier
Dynamic: description
Dynamic: description-content-type
Dynamic: home-page
Dynamic: license
Dynamic: requires-dist
Dynamic: requires-python
Dynamic: summary
